python_sdk/__init__.py
python_sdk/cli.py
python_sdk/client.py
agent_lobbi_sdk-1.0.2.dist-info/METADATA
agent_lobbi_sdk-1.0.2.dist-info/WHEEL
agent_lobbi_sdk-1.0.2.dist-info/entry_points.txt
agent_lobbi_sdk-1.0.2.dist-info/licenses/LICENSE
agent_lobbi_sdk-1.0.2.dist-info/RECORD
